gwpopulation_pipe/__init__.py
gwpopulation_pipe/_version.py
gwpopulation_pipe/analytic_spin_prior.py
gwpopulation_pipe/common_format.py
gwpopulation_pipe/create_injections.py
gwpopulation_pipe/data_analysis.py
gwpopulation_pipe/data_collection.py
gwpopulation_pipe/data_simulation.py
gwpopulation_pipe/main.py
gwpopulation_pipe/parser.py
gwpopulation_pipe/pesumary_plot.py
gwpopulation_pipe/post_plots.py
gwpopulation_pipe/review.py
gwpopulation_pipe/utils.py
gwpopulation_pipe/vt_helper.py
gwpopulation_pipe-0.4.3.dist-info/licenses/LICENSE
gwpopulation_pipe-0.4.3.dist-info/METADATA
gwpopulation_pipe-0.4.3.dist-info/WHEEL
gwpopulation_pipe-0.4.3.dist-info/entry_points.txt
gwpopulation_pipe-0.4.3.dist-info/top_level.txt
gwpopulation_pipe-0.4.3.dist-info/RECORD
